mend_ignore_alerts/__init__.py
mend_ignore_alerts/_version.py
mend_ignore_alerts/conftest.py
mend_ignore_alerts/const.py
mend_ignore_alerts/ignore_alerts.py
mend_ignore_alerts-24.6.1.dist-info/LICENSE
mend_ignore_alerts-24.6.1.dist-info/METADATA
mend_ignore_alerts-24.6.1.dist-info/WHEEL
mend_ignore_alerts-24.6.1.dist-info/entry_points.txt
mend_ignore_alerts-24.6.1.dist-info/top_level.txt
mend_ignore_alerts-24.6.1.dist-info/RECORD
