Metadata-Version: 2.1
Name: mend-ignore-alerts
Version: 24.6.1
Summary: Parse yml file and update alerts
Home-page: https://github.com/mend-toolkit/ignore-alerts
Author: Mend Professional Services
Author-email: ps@mend.io
License: LICENSE.txt
Classifier: Programming Language :: Python :: 3.9
Classifier: Programming Language :: Python :: 3.10
Classifier: Programming Language :: Python :: 3.11
Classifier: License :: OSI Approved :: Apache Software License
Classifier: Operating System :: OS Independent
Requires-Python: >=3.9
License-File: LICENSE
Requires-Dist: configparser ~=5.3.0
Requires-Dist: requests ~=2.31.0
Requires-Dist: setuptools ~=65.5.1
Requires-Dist: PyYAML ~=6.0
Requires-Dist: PyGithub ~=1.59.0
